clinguin/__init__.py
clinguin/client_helper.py
clinguin/parse_input.py
clinguin/server_helper.py
clinguin/show_frontend_syntax_enum.py
clinguin/client/__init__.py
clinguin/client/api/__init__.py
clinguin/client/api/api.py
clinguin/client/api/frontend_operation_dto.py
clinguin/client/application/__init__.py
clinguin/client/application/client_base.py
clinguin/client/presentation/__init__.py
clinguin/client/presentation/abstract_frontend.py
clinguin/client/presentation/frontends/__init__.py
clinguin/client/presentation/frontends/angular_frontend/__init__.py
clinguin/client/presentation/frontends/angular_frontend/angular_frontend.py
clinguin/client/presentation/frontends/angular_frontend/clinguin_angular_frontend/3rdpartylicenses.txt
clinguin/client/presentation/frontends/angular_frontend/clinguin_angular_frontend/favicon.ico
clinguin/client/presentation/frontends/angular_frontend/clinguin_angular_frontend/index.html
clinguin/client/presentation/frontends/angular_frontend/clinguin_angular_frontend/main.43c92bdc249f5746.js
clinguin/client/presentation/frontends/angular_frontend/clinguin_angular_frontend/polyfills.26316270d5c34064.js
clinguin/client/presentation/frontends/angular_frontend/clinguin_angular_frontend/runtime.496fedc6e58b1167.js
clinguin/client/presentation/frontends/angular_frontend/clinguin_angular_frontend/scripts.76a567df885bfa47.js
clinguin/client/presentation/frontends/angular_frontend/clinguin_angular_frontend/styles.1b9129ce3468cf82.css
clinguin/client/presentation/frontends/angular_frontend/clinguin_angular_frontend/assets/config.json
clinguin/client/presentation/frontends/tkinter_frontend/__init__.py
clinguin/client/presentation/frontends/tkinter_frontend/tkinter_frontend.py
clinguin/client/presentation/frontends/tkinter_frontend/tkinter_elements/__init__.py
clinguin/client/presentation/frontends/tkinter_frontend/tkinter_elements/button.py
clinguin/client/presentation/frontends/tkinter_frontend/tkinter_elements/canvas.py
clinguin-2.7.4.dist-info/licenses/LICENSE
clinguin-2.7.4.dist-info/METADATA
clinguin-2.7.4.dist-info/WHEEL
clinguin-2.7.4.dist-info/entry_points.txt
clinguin-2.7.4.dist-info/top_level.txt
clinguin-2.7.4.dist-info/RECORD
