Metadata-Version: 2.4
Name: clinguin
Version: 2.7.4
Summary: An interactive visualizer for clingo
Home-page: https://github.com/krr-up/clinguin
Author: Alexander Beiser, Susana Hahn (Potassco)
Author-email: alexl.id.at@gmail.com, hahnmartin@uni-potsdam.de
License-File: LICENSE
Requires-Dist: clingo<=5.8.0,>=5.7.1
Requires-Dist: clorm>=1.4.1
Requires-Dist: clingo-dl
Requires-Dist: clingcon
Requires-Dist: fastapi
Requires-Dist: networkx
Requires-Dist: uvicorn
Requires-Dist: clingraph
Requires-Dist: Pillow
Requires-Dist: clingexplaid>=1.3.4
Provides-Extra: tkinter
Requires-Dist: tk; extra == "tkinter"
Provides-Extra: doc
Requires-Dist: sphinx==6.2.1; extra == "doc"
Requires-Dist: nbsphinx; extra == "doc"
Requires-Dist: furo; extra == "doc"
Requires-Dist: sphinx_inline_tabs; extra == "doc"
Requires-Dist: sphinx_copybutton; extra == "doc"
Requires-Dist: sphinxemoji; extra == "doc"
Requires-Dist: myst_parser; extra == "doc"
Provides-Extra: test
Requires-Dist: nox; extra == "test"
Provides-Extra: format
Requires-Dist: nox; extra == "format"
Requires-Dist: autoflake; extra == "format"
Requires-Dist: isort; extra == "format"
Requires-Dist: black; extra == "format"
Provides-Extra: lint-flake8
Requires-Dist: nox; extra == "lint-flake8"
Requires-Dist: flake8; extra == "lint-flake8"
Provides-Extra: lint-pylint
Requires-Dist: nox; extra == "lint-pylint"
Requires-Dist: pylint; extra == "lint-pylint"
Dynamic: license-file
